MANIFEST.in
README.md
requirements-gpu.txt
requirements.txt
setup.py
nlp_toolkit/__init__.py
nlp_toolkit/callbacks.py
nlp_toolkit/classifier.py
nlp_toolkit/config.py
nlp_toolkit/data.py
nlp_toolkit/labeler.py
nlp_toolkit/sequence.py
nlp_toolkit/trainer.py
nlp_toolkit/utilities.py
nlp_toolkit/visualization.py
nlp_toolkit.egg-info/PKG-INFO
nlp_toolkit.egg-info/SOURCES.txt
nlp_toolkit.egg-info/dependency_links.txt
nlp_toolkit.egg-info/requires.txt
nlp_toolkit.egg-info/top_level.txt
nlp_toolkit/chunk_segmentor/README.md
nlp_toolkit/chunk_segmentor/__init__.py
nlp_toolkit/chunk_segmentor/segment.py
nlp_toolkit/chunk_segmentor/tagger.py
nlp_toolkit/chunk_segmentor/trie.py
nlp_toolkit/chunk_segmentor/utils.py
nlp_toolkit/data/radical.txt
nlp_toolkit/models/__init__.py
nlp_toolkit/models/base_model.py
nlp_toolkit/models/bi_lstm_att.py
nlp_toolkit/models/char_rnn.py
nlp_toolkit/models/dpcnn.py
nlp_toolkit/models/han.py
nlp_toolkit/models/idcnn.py
nlp_toolkit/models/text_cnn.py
nlp_toolkit/models/transformer.py
nlp_toolkit/models/word_rnn.py
nlp_toolkit/modules/__init__.py
nlp_toolkit/modules/custom_loss.py
nlp_toolkit/modules/logits.py
nlp_toolkit/modules/attentions/__init__.py
nlp_toolkit/modules/attentions/attention.py
nlp_toolkit/modules/attentions/multi_dim_attention.py
nlp_toolkit/modules/attentions/self_attention.py
nlp_toolkit/modules/token_embedders/__init__.py
nlp_toolkit/modules/token_embedders/embedding.py
nlp_toolkit/modules/token_embedders/position_embedding.py