Metadata-Version: 2.1
Name: nlp-toolkit
Version: 1.3.2
Summary: NLP Toolkit with easy model training and applications
Home-page: https://github.com/stevewyl/nlp_toolkit
Author: yilei.wang
Author-email: stevewyl@163.com
License: MIT
Keywords: nlp keras text classification sequence labeling
Platform: UNKNOWN
Classifier: Programming Language :: Python :: 3.6
Classifier: License :: OSI Approved :: MIT License
Classifier: Topic :: Scientific/Engineering :: Artificial Intelligence
Requires-Python: >=3.6
